pdb_toolkit/__init__.py
pdb_toolkit/constants.py
pdb_toolkit/editor/__init__.py
pdb_toolkit/editor/fix_pdb.py
pdb_toolkit/editor/keep_only_atoms.py
pdb_toolkit/editor/protonate_pdb.py
pdb_toolkit/editor/renumber_pdb.py
pdb_toolkit/editor/sort_atoms.py
pdb_toolkit/editor/unprotonate_pdb.py
pdb_toolkit/generic/__init__.py
pdb_toolkit/generic/align.py
pdb_toolkit/generic/concat_pdbs.py
pdb_toolkit/generic/download_pdb.py
pdb_toolkit/generic/extract_chains_from_pdb.py
pdb_toolkit/generic/split_chains.py
pdb_toolkit/parser/__init__.py
pdb_toolkit/parser/get_atoms_residues.py
pdb_toolkit/parser/get_pdb_centroid.py
pdb_toolkit/parser/get_pdb_sequence.py
pdb_toolkit/parser/split_residues_surface_boundary_core.py
pdb_toolkit/parser/steric_clashes.py
pdb_toolkit-0.3.9.dist-info/LICENSE
pdb_toolkit-0.3.9.dist-info/METADATA
pdb_toolkit-0.3.9.dist-info/WHEEL
pdb_toolkit-0.3.9.dist-info/top_level.txt
pdb_toolkit-0.3.9.dist-info/RECORD
