Metadata-Version: 2.1
Name: pdb-toolkit
Version: 0.3.9
Home-page: https://github.com/raoufkeskes/pdb_toolkit
Author: raouf-ks
Author-email: raouf.keskes@mabsilico.com
License: MIT Licence
Classifier: Programming Language :: Python :: 3
Classifier: License :: OSI Approved :: MIT License
Classifier: Operating System :: OS Independent
Requires-Python: >=3.6
License-File: LICENSE
Requires-Dist: wget
Requires-Dist: requests
Requires-Dist: chardet
